dataall_cli/__init__.py
dataall_cli/__main__.py
dataall_cli/bind_commands.py
dataall_cli/cli.py
dataall_cli/utils/__init__.py
dataall_cli/utils/config.py
dataall_cli-0.4.3.dist-info/METADATA
dataall_cli-0.4.3.dist-info/WHEEL
dataall_cli-0.4.3.dist-info/entry_points.txt
dataall_cli-0.4.3.dist-info/licenses/LICENSE
dataall_cli-0.4.3.dist-info/licenses/NOTICE
dataall_cli-0.4.3.dist-info/licenses/NOTICE.txt
dataall_cli-0.4.3.dist-info/RECORD
