Metadata-Version: 2.4
Name: dataall-cli
Version: 0.4.3
Summary: AWS data.all CLI
License: Apache-2.0
License-File: LICENSE
License-File: NOTICE
License-File: NOTICE.txt
Keywords: dataall,aws
Author: Amazon Web Services
Requires-Python: >=3.9,<4.0
Classifier: Programming Language :: Python :: 3.9
Classifier: Programming Language :: Python :: 3.10
Classifier: Programming Language :: Python :: 3.11
Classifier: Programming Language :: Python :: 3.12
Requires-Dist: PyYAML (>=6.0.1)
Requires-Dist: atomicfile (>=1.0.1)
Requires-Dist: boto3 (>=1.40.55)
Requires-Dist: botocore (>=1.40.55)
Requires-Dist: click (>=8.1.6)
Requires-Dist: dataall-core (>=0.4.3)
Requires-Dist: packaging (>=24.2)
Requires-Dist: setuptools ; python_version >= "3.12"
Requires-Dist: typing-extensions (>=4.4.0)
